odoo/addons/account_bank_statement_import_bypass_check/README.rst
odoo/addons/account_bank_statement_import_bypass_check/__init__.py
odoo/addons/account_bank_statement_import_bypass_check/__manifest__.py
odoo/addons/account_bank_statement_import_bypass_check/i18n/account_bank_statement_import_bypass_check.pot
odoo/addons/account_bank_statement_import_bypass_check/i18n/fr.po
odoo/addons/account_bank_statement_import_bypass_check/readme/CONTRIBUTORS.rst
odoo/addons/account_bank_statement_import_bypass_check/readme/DESCRIPTION.rst
odoo/addons/account_bank_statement_import_bypass_check/readme/USAGE.rst
odoo/addons/account_bank_statement_import_bypass_check/static/description/icon.png
odoo/addons/account_bank_statement_import_bypass_check/static/description/index.html
odoo/addons/account_bank_statement_import_bypass_check/wizard/__init__.py
odoo/addons/account_bank_statement_import_bypass_check/wizard/account_bank_statement_import.py
odoo/addons/account_bank_statement_import_bypass_check/wizard/account_bank_statement_import_view.xml
odoo12_addon_account_bank_statement_import_bypass_check-12.0.1.0.0.99.dev4.dist-info/METADATA
odoo12_addon_account_bank_statement_import_bypass_check-12.0.1.0.0.99.dev4.dist-info/WHEEL
odoo12_addon_account_bank_statement_import_bypass_check-12.0.1.0.0.99.dev4.dist-info/top_level.txt
odoo12_addon_account_bank_statement_import_bypass_check-12.0.1.0.0.99.dev4.dist-info/RECORD
